Workbook

Sheet Cover
B2: TATA CONSULTANCY SERVICES (TCS)
B3: Historical Financial Statements | FY2020 – FY2024
B5: Exchange / Ticker | C5: NSE: TCS | BSE: 532540
B6: Sector | C6: Information Technology — IT Services & Consulting
B7: Currency | C7: Indian Rupees (₹ Crores)
B8: Fiscal Year End | C8: March 31
B9: Historical Period | C9: FY2020 (Apr 2019 – Mar 2020) to FY2024 (Apr 2023 – Mar 2024)
B10: Reporting Standard | C10: IFRS (Consolidated)
B11: Last Updated | C11: May 2025
B12: Primary Data Source | C12: TCS Annual Reports, NSE/BSE Filings, Screener.in
B15: Sheets Included
B16: Income Statement | C16: Revenue, EBITDA, EBIT, PAT, margins & EPS — FY2020–FY2024
B17: Balance Sheet | C17: Assets, Liabilities & Equity as at March 31 — FY2020–FY2024
B18: Cash Flow Statement | C18: Operating, Investing & Financing cash flows — FY2020–FY2024
B21: Colour Coding Guide
B22: Blue text | C22: Hardcoded inputs from source financials
B23: Black text | C23: Formulas / calculated values
B24: Green bg | C24: Key profit / cash flow subtotals
B25: Amber bg | C25: Pre-tax profit / investing outflows
B26: Grey bg | C26: Margin % and analytical rows

Sheet Income Statement
B1: TATA CONSULTANCY SERVICES — INCOME STATEMENT (Consolidated)
B2: ₹ in Crores | Fiscal Year ends March 31 | Source: TCS Annual Reports / NSE Filings
C4: FY2020 | D4: FY2021 | E4: FY2022 | F4: FY2023 | G4: FY2024
B5: REVENUE
B6: Net Revenue (IT Services) | C6: 156949 | D6: 164177 | E6: 191754 | F6: 225458 | G6: 240893
B7: OPERATING EXPENSES
B8: Employee Costs & Subcontracting | C8: 97066 | D8: 98025 | E8: 116091 | F8: 140200 | G8: 149566
B9: Other Operating Expenses | C9: 17774 | D9: 19606 | E9: 22606 | F9: 25999 | G9: 27031
B10: Total Operating Expenses | C10: =C8+C9 -> 114840 | D10: =D8+D9 -> 117631 | E10: =E8+E9 -> 138697 | F10: =F8+F9 -> 166199 | G10: =G8+G9 -> 176597
B11: PROFITABILITY
B12: EBITDA | C12: =C6-C10 -> 42109 | D12: =D6-D10 -> 46546 | E12: =E6-E10 -> 53057 | F12: =F6-F10 -> 59259 | G12: =G6-G10 -> 64296
B13: Less: Depreciation & Amortisation | C13: 3529 | D13: 4065 | E13: 4604 | F13: 5022 | G13: 4985
B14: EBIT (Operating Profit) | C14: =C12-C13 -> 38580 | D14: =D12-D13 -> 42481 | E14: =E12-E13 -> 48453 | F14: =F12-F13 -> 54237 | G14: =G12-G13 -> 59311
B15: BELOW THE LINE
B16: Add: Other Income / Investment Income | C16: 4592 | D16: 1916 | E16: 4018 | F16: 3449 | G16: 3464
B17: Less: Finance Costs (Interest) | C17: 924 | D17: 637 | E17: 784 | F17: 779 | G17: 778
B18: Profit Before Tax (PBT) | C18: =C14+C16-C17 -> 42248 | D18: =D14+D16-D17 -> 43760 | E18: =E14+E16-E17 -> 51687 | F18: =F14+F16-F17 -> 56907 | G18: =G14+G16-G17 -> 61997
B19: Less: Tax Expense | C19: 9801 | D19: 11198 | E19: 13238 | F19: 14604 | G19: 15898
B20: Profit After Tax (PAT) | C20: =C18-C19 -> 32447 | D20: =D18-D19 -> 32562 | E20: =E18-E19 -> 38449 | F20: =F18-F19 -> 42303 | G20: =G18-G19 -> 46099
B21: Less: Minority Interest | C21: 380 | D21: 350 | E21: 390 | F21: 456 | G21: 590
B22: PAT Attributable to Shareholders | C22: =C20-C21 -> 32067 | D22: =D20-D21 -> 32212 | E22: =E20-E21 -> 38059 | F22: =F20-F21 -> 41847 | G22: =G20-G21 -> 45509
B23: KEY MARGINS
B24: EBITDA Margin % | C24: =C12/C6 -> 0.26829734 | D24: =D12/D6 -> 0.28351109 | E24: =E12/E6 -> 0.27669305 | F24: =F12/F6 -> 0.26283831 | G24: =G12/G6 -> 0.26690688
B25: EBIT Margin % | C25: =C14/C6 -> 0.24581233 | D25: =D14/D6 -> 0.25875123 | E25: =E14/E6 -> 0.25268313 | F25: =F14/F6 -> 0.24056365 | G25: =G14/G6 -> 0.24621305
B26: PAT Margin % | C26: =C20/C6 -> 0.20673595 | D26: =D20/D6 -> 0.19833472 | E26: =E20/E6 -> 0.20051211 | F26: =F20/F6 -> 0.1876314 | G26: =G20/G6 -> 0.19136712
B27: PER SHARE DATA
B28: EPS (₹) — Basic | C28: 86.19 | D28: 87.67 | E28: 104.75 | F28: 115.19 | G28: 126.88
B29: Dividend Per Share (₹) | C29: 73 | D29: 38 | E29: 43 | F29: 115 | G29: 73
B30: Shares Outstanding (Billion) | C30: 3.75 | D30: 3.7 | E30: 3.66 | F30: 3.66 | G30: 3.62
B32: Source: TCS Annual Reports FY2020–FY2024, NSE/BSE Filings, Screener.in (Consolidated IFRS). All figures in ₹ Crores.

Sheet Balance Sheet
B1: TATA CONSULTANCY SERVICES — BALANCE SHEET (Consolidated)
B2: ₹ in Crores | As at March 31 | Source: TCS Annual Reports / NSE Filings
C4: FY2020 | D4: FY2021 | E4: FY2022 | F4: FY2023 | G4: FY2024
B5: ASSETS
B6: Current Assets
B7: Cash & Cash Equivalents | C7: ='Cash Flow Statement'!C30 -> 14580 | D7: ='Cash Flow Statement'!D30 -> 14700 | E7: ='Cash Flow Statement'!E30 -> 17129 | F7: ='Cash Flow Statement'!F30 -> 15579 | G7: ='Cash Flow Statement'!G30 -> 14555
B8: Short-term Investments / Deposits | C8: 25990 | D8: 29606 | E8: 32109 | F8: 38403 | G8: 34567
B9: Trade Receivables | C9: 33410 | D9: 40492 | E9: 46058 | F9: 55570 | G9: 59423
B10: Other Current Assets | C10: 4800 | D10: 5310 | E10: 7450 | F10: 4535 | G10: 8800
B11: Total Current Assets | C11: =SUM(C7:C10) -> 78780 | D11: =SUM(D7:D10) -> 90108 | E11: =SUM(E7:E10) -> 102746 | F11: =SUM(F7:F10) -> 114087 | G11: =SUM(G7:G10) -> 117345
B12: Non-Current Assets
B14: Property, Plant & Equipment (Net) | C14: 18900 | D14: 19669 | E14: 19615 | F14: 19024 | G14: 18826
B15: Goodwill & Intangibles | C15: 1850 | D15: 1798 | E15: 1787 | F15: 1858 | G15: 1832
B16: Long-term Investments | C16: 720 | D16: 757 | E16: 1268 | F16: 1371 | G16: 2280
B17: Other Non-Current Assets | C17: 7000 | D17: 9396 | E17: 8539 | F17: 9040 | G17: 9540
B18: Total Non-Current Assets | C18: =SUM(C14:C17) -> 28470 | D18: =SUM(D14:D17) -> 31620 | E18: =SUM(E14:E17) -> 31209 | F18: =SUM(F14:F17) -> 31293 | G18: =SUM(G14:G17) -> 32478
B20: TOTAL ASSETS | C20: =C11+C18 -> 107250 | D20: =D11+D18 -> 121728 | E20: =E11+E18 -> 133955 | F20: =F11+F18 -> 145380 | G20: =G11+G18 -> 149823
B21: LIABILITIES & EQUITY
B22: Current Liabilities
B23: Trade Payables & Accrued Expenses | C23: 19628 | D23: 19619 | E23: 18650 | F23: 26516 | G23: 24589
B24: Current Portion of Lease Liabilities | C24: 1200 | D24: 1292 | E24: 1450 | F24: 1485 | G24: 1505
B25: Income Tax Payable | C25: 5500 | D25: 6243 | E25: 7921 | F25: 9345 | G25: 11433
B26: Unearned / Deferred Revenue | C26: 4600 | D26: 4564 | E26: 4669 | F26: 4980 | G26: 5149
B27: Other Current Liabilities | C27: 2500 | D27: 2490 | E27: 3060 | F27: 2202 | G27: 3427
B28: Total Current Liabilities | C28: =SUM(C23:C27) -> 33428 | D28: =SUM(D23:D27) -> 34208 | E28: =SUM(E23:E27) -> 35750 | F28: =SUM(F23:F27) -> 44528 | G28: =SUM(G23:G27) -> 46103
B29: Non-Current Liabilities
B31: Long-term Lease Liabilities | C31: 6200 | D31: 6503 | E31: 6368 | F31: 6203 | G31: 6516
B32: Other Long-term Liabilities | C32: 1800 | D32: 1796 | E32: 1667 | F32: 1688 | G32: 2026
B33: Total Non-Current Liabilities | C33: =SUM(C31:C32) -> 8000 | D33: =SUM(D31:D32) -> 8299 | E33: =SUM(E31:E32) -> 8035 | F33: =SUM(F31:F32) -> 7891 | G33: =SUM(G31:G32) -> 8542
B34: Shareholders' Equity
B36: Equity Share Capital | C36: 375 | D36: 370 | E36: 366 | F36: 366 | G36: 362
B37: Retained Earnings | C37: 59200 | D37: 82558 | E37: 85607 | F37: 86674 | G37: 86427
B38: Other Equity & Reserves | C38: 3450 | D38: 3505 | E38: 3166 | F38: 3384 | G38: 3700
B39: Total Equity (excl. Minority) | C39: =SUM(C36:C38) -> 63025 | D39: =SUM(D36:D38) -> 86433 | E39: =SUM(E36:E38) -> 89139 | F39: =SUM(F36:F38) -> 90424 | G39: =SUM(G36:G38) -> 90489
B40: Minority / Non-Controlling Interest | C40: 600 | D40: 675 | E40: 707 | F40: 782 | G40: 830
B42: TOTAL LIABILITIES & EQUITY | C42: =C28+C33+C39+C40 -> 105053 | D42: =D28+D33+D39+D40 -> 129615 | E42: =E28+E33+E39+E40 -> 133631 | F42: =F28+F33+F39+F40 -> 143625 | G42: =G28+G33+G39+G40 -> 145964
B44: Balance Check (Assets – L&E, should be 0) | C44: =C20-C42 -> 2197 | D44: =D20-D42 -> -7887 | E44: =E20-E42 -> 324 | F44: =F20-F42 -> 1755 | G44: =G20-G42 -> 3859
B46: Source: TCS Annual Reports FY2020–FY2024, NSE/BSE Filings, StockAnalysis.com (S&P Global). All figures in ₹ Crores.

Sheet Cash Flow Statement
B1: TATA CONSULTANCY SERVICES — CASH FLOW STATEMENT (Consolidated)
B2: ₹ in Crores | Fiscal Year ends March 31 | Source: TCS Annual Reports / NSE Filings
C4: FY2020 | D4: FY2021 | E4: FY2022 | F4: FY2023 | G4: FY2024
B5: A. OPERATING ACTIVITIES
B7: Profit After Tax | C7: 32447 | D7: 32562 | E7: 38449 | F7: 42303 | G7: 46099
B8: Add: Depreciation & Amortisation | C8: 3529 | D8: 4065 | E8: 4604 | F8: 5022 | G8: 4985
B9: Changes in Working Capital | C9: 1200 | D9: 2800 | E9: -1500 | F9: -3200 | G9: -1800
B10: Tax Adjustments & Deferred Tax | C10: -500 | D10: -900 | E10: -1200 | F10: -1100 | G10: -1400
B11: Other Non-Cash / Adjustments | C11: 800 | D11: 500 | E11: 600 | F11: 700 | G11: 900
B12: Net Cash from Operating Activities (CFO) | C12: =SUM(C7:C11) -> 37476 | D12: =SUM(D7:D11) -> 39027 | E12: =SUM(E7:E11) -> 40953 | F12: =SUM(F7:F11) -> 43725 | G12: =SUM(G7:G11) -> 48784
B13: B. INVESTING ACTIVITIES
B15: Capital Expenditure (Capex) | C15: -3200 | D15: -2800 | E15: -2900 | F15: -3500 | G15: -3800
B16: Acquisitions / Business Combinations | C16: -200 | D16: -150 | E16: -500 | F16: -300 | G16: -500
B17: Net Purchase / (Sale) of Investments | C17: 1500 | D17: -5200 | E17: -800 | F17: 1500 | G17: -1200
B18: Net Cash from Investing Activities (CFI) | C18: =SUM(C15:C17) -> -1900 | D18: =SUM(D15:D17) -> -8150 | E18: =SUM(E15:E17) -> -4200 | F18: =SUM(F15:F17) -> -2300 | G18: =SUM(G15:G17) -> -5500
B19: C. FINANCING ACTIVITIES
B21: Dividends Paid | C21: -27375 | D21: -14070 | E21: -15740 | F21: -42096 | G21: -26680
B22: Share Buyback | C22: 0 | D22: -16000 | E22: -18000 | F22: 0 | G22: -17000
B23: Finance Costs Paid | C23: -924 | D23: -637 | E23: -784 | F23: -779 | G23: -778
B24: Net Cash from Financing Activities (CFF) | C24: =SUM(C21:C23) -> -28299 | D24: =SUM(D21:D23) -> -30707 | E24: =SUM(E21:E23) -> -34524 | F24: =SUM(F21:F23) -> -42875 | G24: =SUM(G21:G23) -> -44458
B25: D. NET MOVEMENT
B26: Effect of Exchange Rate Changes on Cash | C26: 100 | D26: -50 | E26: 200 | F26: -100 | G26: 150
B27: Net Increase / (Decrease) in Cash | C27: =C12+C18+C24+C26 -> 7377 | D27: =D12+D18+D24+D26 -> 120 | E27: =E12+E18+E24+E26 -> 2429 | F27: =F12+F18+F24+F26 -> -1550 | G27: =G12+G18+G24+G26 -> -1024
B29: Opening Cash & Cash Equivalents | C29: 7203 | D29: =C30 -> 14580 | E29: =D30 -> 14700 | F29: =E30 -> 17129 | G29: =F30 -> 15579
B30: Closing Cash & Cash Equivalents | C30: =C27+C29 -> 14580 | D30: =D27+D29 -> 14700 | E30: =E27+E29 -> 17129 | F30: =F27+F29 -> 15579 | G30: =G27+G29 -> 14555
B31: FREE CASH FLOW SUMMARY
B32: Free Cash Flow (CFO + Capex) | C32: =C12+C15 -> 34276 | D32: =D12+D15 -> 36227 | E32: =E12+E15 -> 38053 | F32: =F12+F15 -> 40225 | G32: =G12+G15 -> 44984
B33: FCF Conversion (FCF / PAT) | D33: =(D32)/D7 -> 1.1125545 | E33: =(E32)/E7 -> 0.98970064 | F33: =(F32)/F7 -> 0.95087819 | G33: =(G32)/G7 -> 0.97581292
B34: Capex / Revenue (Capex Intensity) | C34: =ABS(C15)/'Income Statement'!C6 -> 0.020388789 | D34: =ABS(D15)/'Income Statement'!D6 -> 0.017054764 | E34: =ABS(E15)/'Income Statement'!E6 -> 0.015123544 | F34: =ABS(F15)/'Income Statement'!F6 -> 0.015523956 | G34: =ABS(G15)/'Income Statement'!G6 -> 0.015774639

Sheet Assumptions Sheet
B2: TCS — PROJECTION ASSUMPTIONS | FY2025E – FY2029E
B3: Blue cells = editable inputs | Black cells = formulas | All ₹ figures in Crores
B4: Assumption | C4: FY25E | D4: FY26E | E4: FY27E | F4: FY28E | G4: FY29E | I4: Rationale / How We Got This
B5: INCOME STATEMENT ASSUMPTIONS
B6: Revenue Growth % | C6: 0.07 | D6: 0.09 | E6: 0.1 | F6: 0.1 | G6: 0.09 | I6: Historical 4-yr CAGR is 11.3%, but FY24 slowed to 6.8% due to weak BFSI demand. Start conservative at 7%, recover as AI/cloud spend picks up, then taper back toward end of period.
B7: Employee Cost % of Revenue | C7: 0.62 | D7: 0.615 | E7: 0.61 | F7: 0.61 | G7: 0.61 | I7: Stable between 59.7%–62.2% historically. Slight improvement assumed as automation and pyramid optimisation offset ongoing wage inflation.
B8: Other Opex % of Revenue | C8: 0.112 | D8: 0.11 | E8: 0.11 | F8: 0.108 | G8: 0.108 | I8: Trending down from 11.9% (FY21) → 11.2% (FY24). Modest operating leverage on fixed cost base as revenue scales.
B9: D&A % of Revenue | C9: 0.021 | D9: 0.02 | E9: 0.02 | F9: 0.02 | G9: 0.02 | I9: Flat at 2.1–2.2% across all 5 historical years. No major new capex cycle expected; held stable.
B10: Other Income (₹ Cr) | C10: 3500 | D10: 3600 | E10: 3700 | F10: 3800 | G10: 3900 | I10: FY22–FY24 averaged ~₹3,644 Cr (excluding the FY21 anomaly of ₹1,916 Cr). Gentle growth as cash & investment balances build over time.
B11: Finance Costs (₹ Cr) | C11: 780 | D11: 780 | E11: 780 | F11: 780 | G11: 780 | I11: Essentially flat at ₹778–779 Cr for three consecutive years. TCS carries no significant financial debt; held constant.
B12: Effective Tax Rate % | C12: 0.255 | D12: 0.255 | E12: 0.255 | F12: 0.255 | G12: 0.255 | I12: Remarkably stable at 25.6% every year since FY21. Rounded to 25.5% as a clean, stable forward assumption.
B13: Assumption | C13: FY25E | D13: FY26E | E13: FY27E | F13: FY28E | G13: FY29E | I13: Rationale / How We Got This
B14: CASH FLOW ASSUMPTIONS
B15: Capex % of Revenue | C15: 0.016 | D15: 0.016 | E15: 0.016 | F15: 0.016 | G15: 0.016 | I15: Held flat at FY23–FY24 average of 1.6%. TCS is highly asset-light; no major infrastructure or capacity build-out expected over the projection period.
B16: Acquisitions (in Cr) | C16: -400 | D16: -400 | E16: -500 | F16: -500 | G16: -500 | I16: Historical range ₹150–₹500 Cr/yr. TCS does bolt-on acquisitions, not transformational deals. Modest ~₹400–500 Cr/yr assumed.
B17: Net investment purchases (In Cr) | C17: -800 | D17: -800 | E17: -800 | F17: -800 | G17: -800 | I17: Highly variable historically (−₹5,200 to +₹1,500 Cr). Assume a moderate net outflow as TCS continues building its long-term investment portfolio steadily.
B18: Dvidends Paid (Cr) | C18: -20500 | D18: -22150 | E18: -26300 | F18: -30650 | G18: -32650 | I18: Derived as DPS × shares outstanding. Payout ratio ~45% of PAT as regular dividends. Historically variable (special dividends cause spikes); normalised here to a ~45% ordinary payout.
B19: Share buybacks (in Cr) | C19: -17000 | D19: _ | E19: -18000 | F19: _ | G19: -19000 | I19: TCS has done 3 buybacks in 5 years (FY21: ₹16,000 Cr, FY22: ₹18,000 Cr, FY24: ₹17,000 Cr). Pattern suggests ~every alternate year. Modelled accordingly with slight size increase.
B20: Finance costs paid (in Cr) | C20: -780 | D20: -780 | E20: -780 | F20: -780 | G20: -780 | I20: Mirrors finance cost in P&L — flat at ₹780 Cr. TCS has no bank debt; this is purely lease interest.
B21: Forex impact on cash (in Cr) | C21: 100 | D21: 100 | E21: 100 | F21: 100 | G21: 100 | I21: Small and variable (±₹200 Cr historically). Held at a nominal +₹100 Cr/yr — immaterial to the model.
B22: Working Capital Changes | C22: -1800 | D22: -2000 | E22: -2200 | F22: -2500 | G22: -2500 | I22: Negative in FY22–FY24 (receivables growing with revenue). As revenue grows, working capital absorbs more cash. Mild outflow increasing in line with revenue scale.
B23: Assumption | C23: FY25E | D23: FY26E | E23: FY27E | F23: FY28E | G23: FY29E | I23: Rationale / How We Got This
B24: BALANCE SHEET ASSUMPTIONS
B25: Short-Term Investments- growth | C25: 0.06 | D25: 0.06 | E25: 0.06 | F25: 0.06 | G25: 0.06 | I25: Grew at ~7% CAGR (FY20–FY24): ₹25,990 → ₹34,567 Cr. Surplus FCF gets parked here. Slight moderation as shareholder payouts increase.
B26: Trade Receivables - DSO(days) | C26: 88 | D26: 88 | E26: 88 | F26: 87 | G26: 87 | I26: DSO stable at ~77–90 days historically. FY24 implied DSO ≈ 90 days. Held at 88 days; a 1-day tightening in later years reflects minor collections improvement. Formula: DSO × Revenue ÷ 365.
B27: Other Current Assets - % of revenue | C27: 0.038 | D27: 0.038 | E27: 0.037 | F27: 0.037 | G27: 0.037 | I27: Range was 2.0%–3.9% historically. FY24 was 3.7%. Held near that level — includes prepayments, advance tax, and other receivables that scale broadly with revenue.
B28: Goodwill and Intangibles | C28: 1830 | D28: 1830 | E28: 1830 | F28: 1830 | G28: 1830 | I28: Flat at ~₹1,830 Cr (FY24: ₹1,832 Cr). Minimal M&A activity assumed; small amortisation offset by any bolt-on acquisitions. Adjust if a large deal is modelled.
B29: Long term Investments - Annual addition | C29: 250 | D29: 250 | E29: 250 | F29: 250 | G29: 260 | I29: Grew from ₹720 → ₹2,280 Cr over 4 years. Represents strategic equity stakes and associate investments. Adding ~₹250 Cr/yr is consistent with the recent pace.
B30: Other Non Current Assets - % of revenue | C30: 0.255 | D30: 0.255 | E30: 0.255 | F30: 0.255 | G30: 0.255 | I30: Remarkably stable at 25.6% every year since FY21. Rounded to 25.5% as a clean, stable forward assumption.
B31: Trade Payables - DPO (days) | C31: 52 | D31: 52 | E31: 52 | F31: 50 | G31: 50 | I31: Dominated by salary accruals (employee cost is ~61% of revenue). DPO on total opex was ~46–60 days. Formula: DPO × Total Opex ÷ 365. Slight tightening in later years as operational efficiency improves.
B32: Current lease liabilities (in Cr.) | C32: 1540 | D32: 1570 | E32: 1600 | F32: 1640 | G32: 1675 | I32: Flat historically at ₹1,200–₹1,505 Cr (current portion of operating leases). Grown ~2–3% YoY for gradual office footprint additions globally.
B33: income Tax Payable - % of tax expense | C33: 0.72 | D33: 0.72 | E33: 0.72 | F33: 0.72 | G33: 0.72 | I33: Rose from ₹5,500 → ₹11,433 Cr tracking profitability. ~70–75% of the annual tax charge sits unpaid at year-end (advance tax timing). Linked to projected tax expense × 72%.
B34: Unearned Revenues - % of revenue | C34: 0.021 | D34: 0.021 | E34: 0.021 | F34: 0.021 | G34: 0.021 | I34: Extremely stable at 2.0–2.1% of revenue across all 5 years. Represents advance billing on multi-year IT contracts. Hold flat.
B35: Other Current Liabilities - % of revenue | C35: 0.013 | D35: 0.013 | E35: 0.013 | F35: 0.013 | G35: 0.013 | I35: Range ₹2,202–₹3,427 Cr (1.0%–1.5% of revenue). Includes statutory dues and employee-related payables. FY24: ~1.4%. Conservative at 1.3%.
B36: Long term lease liabilities - growth | C36: 6600 | D36: 6700 | E36: 6800 | F36: 6900 | G36: 7000 | I36: Flat at ₹6,200–₹6,516 Cr historically. TCS has a large global real-estate footprint. Growing ~1.5% YoY for incremental lease additions and renewals at higher rents.
... B40: Minority interest - growth | C40: 0.05 | D40: 0.05 | E40: 0.05 | F40: 0.05 | G40: 0.05 | I40: Steadily rising: ₹600 → ₹830 Cr. Represents NCI in TCS subsidiaries (e.g. TCS Japan, TCS ibis). Grown ~5% YoY consistently — hold at that rate.

Sheet Projected P&L
A1: TATA CONSULTANCY SERVICES — INCOME STATEMENT (Projected)
B4: FY2025 | C4: FY2026 | D4: FY2027 | E4: FY2028 | F4: FY2029
A5: REVENUE
A6: Net Revenue (IT Services) | B6: ='Income Statement'!C6*(1+'Assumptions Sheet'!C6) -> 167935.43 | C6: ='Income Statement'!D6*(1+'Assumptions Sheet'!D6) -> 178952.93 | D6: ='Income Statement'!E6*(1+'Assumptions Sheet'!E6) -> 210929.4 | E6: ='Income Statement'!F6*(1+'Assumptions Sheet'!F6) -> 248003.8 | F6: ='Income Statement'!G6*(1+'Assumptions Sheet'!G6) -> 262573.37
A7: OPERATING EXPENSES
A8: Employee Costs & Subcontracting | B8: =B6*'Assumptions Sheet'!C7 -> 104119.97 | C8: =C6*'Assumptions Sheet'!D7 -> 110056.05 | D8: =D6*'Assumptions Sheet'!E7 -> 128666.93 | E8: =E6*'Assumptions Sheet'!F7 -> 151282.32 | F8: =F6*'Assumptions Sheet'!G7 -> 160169.76
A9: Other Operating Expenses | B9: ='Income Statement'!C9*'Assumptions Sheet'!C8 -> 1990.688 | C9: ='Income Statement'!D9*'Assumptions Sheet'!D8 -> 2156.66 | D9: ='Income Statement'!E9*'Assumptions Sheet'!E8 -> 2486.66 | E9: ='Income Statement'!F9*'Assumptions Sheet'!F8 -> 2807.892 | F9: ='Income Statement'!G9*'Assumptions Sheet'!G8 -> 2919.348
A10: Total Operating Expenses | B10: =B8+B9 -> 106110.65 | C10: =C8+C9 -> 112212.71 | D10: =D8+D9 -> 131153.59 | E10: =E8+E9 -> 154090.21 | F10: =F8+F9 -> 163089.1
A11: PROFITABILITY
A12: EBITDA | B12: =B6-B10 -> 61824.775 | C12: =C6-C10 -> 66740.218 | D12: =D6-D10 -> 79775.806 | E12: =E6-E10 -> 93913.59 | F12: =F6-F10 -> 99484.266
A13: Less: Depreciation & Amortisation | B13: =B6*'Assumptions Sheet'!C9 -> 3526.644 | C13: =C6*'Assumptions Sheet'!D9 -> 3579.0586 | D13: =D6*'Assumptions Sheet'!E9 -> 4218.588 | E13: =E6*'Assumptions Sheet'!F9 -> 4960.076 | F13: =F6*'Assumptions Sheet'!G9 -> 5251.4674
A14: EBIT (Operating Profit) | B14: =B12-B13 -> 58298.131 | C14: =C12-C13 -> 63161.159 | D14: =D12-D13 -> 75557.218 | E14: =E12-E13 -> 88953.514 | F14: =F12-F13 -> 94232.799
A15: BELOW THE LINE
A16: Add: Other Income / Investment Income | B16: ='Assumptions Sheet'!C10 -> 3500 | C16: ='Assumptions Sheet'!D10 -> 3600 | D16: ='Assumptions Sheet'!E10 -> 3700 | E16: ='Assumptions Sheet'!F10 -> 3800 | F16: ='Assumptions Sheet'!G10 -> 3900
A17: Less: Finance Costs (Interest) | B17: ='Assumptions Sheet'!C11 -> 780 | C17: ='Assumptions Sheet'!D11 -> 780 | D17: ='Assumptions Sheet'!E11 -> 780 | E17: ='Assumptions Sheet'!F11 -> 780 | F17: ='Assumptions Sheet'!G11 -> 780
A18: Profit Before Tax (PBT) | B18: =B14+B16-B17 -> 61018.131 | C18: =C14+C16-C17 -> 65981.159 | D18: =D14+D16-D17 -> 78477.218 | E18: =E14+E16-E17 -> 91973.514 | F18: =F14+F16-F17 -> 97352.799
A19: Less: Tax Expense | B19: ='Projected P&L'!B18*'Assumptions Sheet'!C12 -> 15559.623 | C19: ='Projected P&L'!C18*'Assumptions Sheet'!D12 -> 16825.196 | D19: ='Projected P&L'!D18*'Assumptions Sheet'!E12 -> 20011.691 | E19: ='Projected P&L'!E18*'Assumptions Sheet'!F12 -> 23453.246 | F19: ='Projected P&L'!F18*'Assumptions Sheet'!G12 -> 24824.964
A20: Profit After Tax (PAT) | B20: =B18-B19 -> 45458.508 | C20: =C18-C19 -> 49155.964 | D20: =D18-D19 -> 58465.527 | E20: =E18-E19 -> 68520.268 | F20: =F18-F19 -> 72527.835
A21: Less: Minority Interest | B21: 415 | C21: 415 | D21: 415 | E21: 415 | F21: 415
A22: PAT Attributable to Shareholders | B22: =B20-B21 -> 45043.508 | C22: =C20-C21 -> 48740.964 | D22: =D20-D21 -> 58050.527 | E22: =E20-E21 -> 68105.268 | F22: =F20-F21 -> 72112.835
A23: KEY MARGINS
A24: EBITDA Margin % | B24: =B12/B6 -> 0.36814611 | C24: =C12/C6 -> 0.37294845 | D24: =D12/D6 -> 0.37821094 | E24: =E12/E6 -> 0.37867803 | F24: =F12/F6 -> 0.37888178
A25: EBIT Margin % | B25: =B14/B6 -> 0.34714611 | C25: =C14/C6 -> 0.35294845 | D25: =D14/D6 -> 0.35821094 | E25: =E14/E6 -> 0.35867803 | F25: =F14/F6 -> 0.35888178
A26: PAT Margin % | B26: =B20/B6 -> 0.27069039 | C26: =C20/C6 -> 0.27468655 | D26: =D20/D6 -> 0.27718055 | E26: =E20/E6 -> 0.27628717 | F26: =F20/F6 -> 0.27621931
A27: PER SHARE DATA
A28: EPS (₹) — Basic | B28: =B22/(B30*100) -> 125.43304 | C28: =C22/(C30*100) -> 136.82397 | D28: =D22/(D30*100) -> 164.27164 | E28: =E22/(E30*100) -> 194.27882 | F28: =F22/(F30*100) -> 207.36986
A29: Dividend Per Share (₹) | B29: =B22*0.45/(B30*100) -> 56.44487 | C29: =C22*0.45/(C30*100) -> 61.570788 | D29: =D22*0.45/(D30*100) -> 73.922236 | E29: =E22*0.45/(E30*100) -> 87.425467 | F29: =F22*0.45/(F30*100) -> 93.316438
A30: Shares Outstanding (Billion) | B30: =3.62*(1-0.008) -> 3.59104 | C30: =B30*(1-0.008) -> 3.5623117 | D30: =C30*(1-0.008) -> 3.5338132 | E30: =D30*(1-0.008) -> 3.5055427 | F30: =E30*(1-0.008) -> 3.4774983

Sheet Projected BS
A1: TATA CONSULTANCY SERVICES — BALANCE SHEET (Projected)
B4: FY2025 | C4: FY2026 | D4: FY2027 | E4: FY2028 | F4: FY2029
A5: ASSETS
A6: Current Assets
A7: Cash & Cash Equivalents | B7: ='Projected CF'!B30 -> 24122.119 | C7: ='Projected CF'!C30 -> 27540.388 | D7: ='Projected CF'!D30 -> 24744.374 | E7: ='Projected CF'!E30 -> 30462.779 | F7: ='Projected CF'!F30 -> 32488.255
A8: Short-term Investments / Deposits | B8: ='Balance Sheet'!G8*(1+'Assumptions Sheet'!C25) -> 36641.02 | C8: =B8*(1+'Assumptions Sheet'!D25) -> 38839.481 | D8: =C8*(1+'Assumptions Sheet'!E25) -> 41169.85 | E8: =D8*(1+'Assumptions Sheet'!F25) -> 43640.041 | F8: =E8*(1+'Assumptions Sheet'!G25) -> 46258.444
A9: Trade Receivables | B9: ='Assumptions Sheet'!C26*('Projected P&L'!B6/365) -> 40488.542 | C9: ='Assumptions Sheet'!D26*('Projected P&L'!C6/365) -> 43144.816 | D9: ='Assumptions Sheet'!E26*('Projected P&L'!D6/365) -> 50854.212 | E9: ='Assumptions Sheet'!F26*('Projected P&L'!E6/365) -> 59113.235 | F9: ='Assumptions Sheet'!G26*('Projected P&L'!F6/365) -> 62585.981
A10: Other Current Assets | B10: ='Projected P&L'!B6*'Assumptions Sheet'!C27 -> 6381.5463 | C10: ='Projected P&L'!C6*'Assumptions Sheet'!D27 -> 6800.2113 | D10: ='Projected P&L'!D6*'Assumptions Sheet'!E27 -> 7804.3878 | E10: ='Projected P&L'!E6*'Assumptions Sheet'!F27 -> 9176.1406 | F10: ='Projected P&L'!F6*'Assumptions Sheet'!G27 -> 9715.2147
A11: Total Current Assets | B11: =SUM(B7:B10) -> 107633.23 | C11: =SUM(C7:C10) -> 116324.9 | D11: =SUM(D7:D10) -> 124572.82 | E11: =SUM(E7:E10) -> 142392.19 | F11: =SUM(F7:F10) -> 151047.89
A12: Non-Current Assets
A14: Property, Plant & Equipment (Net) | B14: ='Balance Sheet'!G14+'Projected CF'!B15-'Projected CF'!B8 -> 17986.323 | C14: =B14+'Projected CF'!C15-'Projected CF'!C8 -> 17270.511 | D14: =C14+'Projected CF'!D15-'Projected CF'!D8 -> 16426.794 | E14: =D14+'Projected CF'!E15-'Projected CF'!E8 -> 15434.778 | F14: =E14+'Projected CF'!F15-'Projected CF'!F8 -> 14384.485
A15: Goodwill & Intangibles | B15: ='Assumptions Sheet'!C28 -> 1830 | C15: ='Assumptions Sheet'!D28 -> 1830 | D15: ='Assumptions Sheet'!E28 -> 1830 | E15: ='Assumptions Sheet'!F28 -> 1830 | F15: ='Assumptions Sheet'!G28 -> 1830
A16: Long-term Investments | B16: ='Balance Sheet'!C16+'Assumptions Sheet'!C29 -> 970 | C16: =B16+250 -> 1220 | D16: =C16+250 -> 1470 | E16: =D16+250 -> 1720 | F16: =E16+250 -> 1970
A17: Other Non-Current Assets | B17: ='Income Statement'!C6*'Assumptions Sheet'!C30 -> 40021.995 | C17: ='Income Statement'!D6*'Assumptions Sheet'!D30 -> 41865.135 | D17: ='Income Statement'!E6*'Assumptions Sheet'!E30 -> 48897.27 | E17: ='Income Statement'!F6*'Assumptions Sheet'!F30 -> 57491.79 | F17: ='Income Statement'!G6*'Assumptions Sheet'!G30 -> 61427.715
A18: Total Non-Current Assets | B18: =SUM(B14:B17) -> 60808.318 | C18: =SUM(C14:C17) -> 62185.646 | D18: =SUM(D14:D17) -> 68624.064 | E18: =SUM(E14:E17) -> 76476.568 | F18: =SUM(F14:F17) -> 79612.2
A20: TOTAL ASSETS | B20: =B11+B18 -> 168441.54 | C20: =C11+C18 -> 178510.54 | D20: =D11+D18 -> 193196.89 | E20: =E11+E18 -> 218868.76 | F20: =F11+F18 -> 230660.09
A21: LIABILITIES & EQUITY
A22: Current Liabilities
A23: Trade Payables & Accrued Expenses | B23: ='Assumptions Sheet'!C31*('Income Statement'!C10/365) -> 16360.767 | C23: ='Assumptions Sheet'!D31*('Income Statement'!D10/365) -> 16758.389 | D23: ='Assumptions Sheet'!E31*('Income Statement'!E10/365) -> 19759.573 | E23: ='Assumptions Sheet'!F31*('Income Statement'!F10/365) -> 22766.986 | F23: ='Assumptions Sheet'!G31*('Income Statement'!G10/365) -> 24191.37
A24: Current Portion of Lease Liabilities | B24: ='Assumptions Sheet'!C32 -> 1540 | C24: ='Assumptions Sheet'!D32 -> 1570 | D24: ='Assumptions Sheet'!E32 -> 1600 | E24: ='Assumptions Sheet'!F32 -> 1640 | F24: ='Assumptions Sheet'!G32 -> 1675
A25: Income Tax Payable | B25: ='Income Statement'!C19*'Assumptions Sheet'!C33 -> 7056.72 | C25: ='Income Statement'!D19*'Assumptions Sheet'!D33 -> 8062.56 | D25: ='Income Statement'!E19*'Assumptions Sheet'!E33 -> 9531.36 | E25: ='Income Statement'!F19*'Assumptions Sheet'!F33 -> 10514.88 | F25: ='Income Statement'!G19*'Assumptions Sheet'!G33 -> 11446.56
A26: Unearned / Deferred Revenue | B26: ='Projected P&L'!B6*'Assumptions Sheet'!C34 -> 3526.644 | C26: ='Projected P&L'!C6*'Assumptions Sheet'!D34 -> 3758.0115 | D26: ='Projected P&L'!D6*'Assumptions Sheet'!E34 -> 4429.5174 | E26: ='Projected P&L'!E6*'Assumptions Sheet'!F34 -> 5208.0798 | F26: ='Projected P&L'!F6*'Assumptions Sheet'!G34 -> 5514.0408
A27: Other Current Liabilities | B27: ='Projected P&L'!B6*'Assumptions Sheet'!C35 -> 2183.1606 | C27: ='Projected P&L'!C6*'Assumptions Sheet'!D35 -> 2326.3881 | D27: ='Projected P&L'!D6*'Assumptions Sheet'!E35 -> 2742.0822 | E27: ='Projected P&L'!E6*'Assumptions Sheet'!F35 -> 3224.0494 | F27: ='Projected P&L'!F6*'Assumptions Sheet'!G35 -> 3413.4538
A28: Total Current Liabilities | B28: =SUM(B23:B27) -> 30667.292 | C28: =SUM(C23:C27) -> 32475.349 | D28: =SUM(D23:D27) -> 38062.532 | E28: =SUM(E23:E27) -> 43353.996 | F28: =SUM(F23:F27) -> 46240.424
A29: Non-Current Liabilities
A31: Long-term Lease Liabilities | B31: ='Assumptions Sheet'!C36 -> 6600 | C31: ='Assumptions Sheet'!D36 -> 6700 | D31: ='Assumptions Sheet'!E36 -> 6800 | E31: ='Assumptions Sheet'!F36 -> 6900 | F31: ='Assumptions Sheet'!G36 -> 7000
A32: Other Long-term Liabilities | B32: ='Balance Sheet'!G32*(1+'Assumptions Sheet'!C37) -> 2096.91 | C32: =B32*(1+'Assumptions Sheet'!D37) -> 2170.3018 | D32: =C32*(1+'Assumptions Sheet'!E37) -> 2246.2624 | E32: =D32*(1+'Assumptions Sheet'!F37) -> 2324.8816 | F32: =E32*(1+'Assumptions Sheet'!G37) -> 2406.2525
A33: Total Non-Current Liabilities | B33: =SUM(B31:B32) -> 8696.91 | C33: =SUM(C31:C32) -> 8870.3018 | D33: =SUM(D31:D32) -> 9046.2624 | E33: =SUM(E31:E32) -> 9224.8816 | F33: =SUM(F31:F32) -> 9406.2525
A34: Shareholders' Equity
A36: Equity Share Capital | B36: ='Assumptions Sheet'!C38 -> 358 | C36: ='Assumptions Sheet'!D38 -> 355 | D36: ='Assumptions Sheet'!E38 -> 352 | E36: ='Assumptions Sheet'!F38 -> 349 | F36: ='Assumptions Sheet'!G38 -> 346
A37: Retained Earnings | B37: =B20-(B23+B24+B25+B26+B27+B31+B32+B36+B38+B40) -> 124067.84 | C37: =C20-(C23+C24+C25+C26+C27+C31+C32+C36+C38+C40) -> 132034.82 | D37: =D20-(D23+D24+D25+D26+D27+D31+D32+D36+D38+D40) -> 140835.26 | E37: =E20-(E23+E24+E25+E26+E27+E31+E32+E36+E38+E40) -> 160912.02 | F37: =F20-(F23+F24+F25+F26+F27+F31+F32+F36+F38+F40) -> 169508.1
A38: Other Equity & Reserves | B38: ='Assumptions Sheet'!C39 -> 3780 | C38: ='Assumptions Sheet'!D39 -> 3860 | D38: ='Assumptions Sheet'!E39 -> 3940 | E38: ='Assumptions Sheet'!F39 -> 4020 | F38: ='Assumptions Sheet'!G39 -> 4100
A39: Total Equity (excl. Minority) | B39: =SUM(B36:B38) -> 128205.84 | C39: =SUM(C36:C38) -> 136249.82 | D39: =SUM(D36:D38) -> 145127.26 | E39: =SUM(E36:E38) -> 165281.02 | F39: =SUM(F36:F38) -> 173954.1
A40: Minority / Non-Controlling Interest | B40: ='Balance Sheet'!G40*(1+5%) -> 871.5 | C40: =B40*(1+5%) -> 915.075 | D40: =C40*(1+5%) -> 960.82875 | E40: =D40*(1+5%) -> 1008.8702 | F40: =E40*(1+5%) -> 1059.3137
A42: TOTAL LIABILITIES & EQUITY | B42: =B28+B33+B39+B40 -> 168441.54 | C42: =C28+C33+C39+C40 -> 178510.54 | D42: =D28+D33+D39+D40 -> 193196.89 | E42: =E28+E33+E39+E40 -> 218868.76 | F42: =F28+F33+F39+F40 -> 230660.09
A44: Balance Check (Assets – L&E, should be 0) | B44: =B20-B42 -> 0 | C44: =C20-C42 -> 0 | D44: =D20-D42 -> 0 | E44: =E20-E42 -> 0 | F44: =F20-F42 -> 0

Sheet Projected CF
A1: TATA CONSULTANCY SERVICES — CASH FLOW STATEMENT (Projected)
B4: FY2025 | C4: FY2026 | D4: FY2027 | E4: FY2028 | F4: FY2029
A5: A. OPERATING ACTIVITIES
A7: Profit After Tax | B7: ='Projected P&L'!B20 -> 45458.508 | C7: ='Projected P&L'!C20 -> 49155.964 | D7: ='Projected P&L'!D20 -> 58465.527 | E7: ='Projected P&L'!E20 -> 68520.268 | F7: ='Projected P&L'!F20 -> 72527.835
A8: Add: Depreciation & Amortisation | B8: ='Projected P&L'!B13 -> 3526.644 | C8: ='Projected P&L'!C13 -> 3579.0586 | D8: ='Projected P&L'!D13 -> 4218.588 | E8: ='Projected P&L'!E13 -> 4960.076 | F8: ='Projected P&L'!F13 -> 5251.4674
A9: Changes in Working Capital | B9: ='Assumptions Sheet'!C22 -> -1800 | C9: ='Assumptions Sheet'!D22 -> -2000 | D9: ='Assumptions Sheet'!E22 -> -2200 | E9: ='Assumptions Sheet'!F22 -> -2500 | F9: ='Assumptions Sheet'!G22 -> -2500
A10: Tax Adjustments & Deferred Tax | B10: ='Cash Flow Statement'!G10-225 -> -1625 | C10: =B10-225 -> -1850 | D10: =C10-225 -> -2075 | E10: =D10-225 -> -2300 | F10: =E10-225 -> -2525
A11: Other Non-Cash / Adjustments | B11: =700 -> 700 | C11: =700 -> 700 | D11: =700 -> 700 | E11: =700 -> 700 | F11: =700 -> 700
A12: Net Cash from Operating Activities (CFO) | B12: =SUM(B7:B11) -> 46260.152 | C12: =SUM(C7:C11) -> 49585.022 | D12: =SUM(D7:D11) -> 59109.115 | E12: =SUM(E7:E11) -> 69380.344 | F12: =SUM(F7:F11) -> 73454.303
A13: B. INVESTING ACTIVITIES
A15: Capital Expenditure (Capex) | B15: ='Projected P&L'!B6*'Assumptions Sheet'!C15 -> 2686.9669 | C15: ='Projected P&L'!C6*'Assumptions Sheet'!D15 -> 2863.2469 | D15: ='Projected P&L'!D6*'Assumptions Sheet'!E15 -> 3374.8704 | E15: ='Projected P&L'!E6*'Assumptions Sheet'!F15 -> 3968.0608 | F15: ='Projected P&L'!F6*'Assumptions Sheet'!G15 -> 4201.1739
A16: Acquisitions / Business Combinations | B16: ='Assumptions Sheet'!C16 -> -400 | C16: ='Assumptions Sheet'!D16 -> -400 | D16: ='Assumptions Sheet'!E16 -> -500 | E16: ='Assumptions Sheet'!F16 -> -500 | F16: ='Assumptions Sheet'!G16 -> -500
A17: Net Purchase / (Sale) of Investments | B17: ='Assumptions Sheet'!C17 -> -800 | C17: ='Assumptions Sheet'!D17 -> -800 | D17: ='Assumptions Sheet'!E17 -> -800 | E17: ='Assumptions Sheet'!F17 -> -800 | F17: ='Assumptions Sheet'!G17 -> -800
A18: Net Cash from Investing Activities (CFI) | B18: =SUM(B15:B17) -> 1486.9669 | C18: =SUM(C15:C17) -> 1663.2469 | D18: =SUM(D15:D17) -> 2074.8704 | E18: =SUM(E15:E17) -> 2668.0608 | F18: =SUM(F15:F17) -> 2901.1739
A19: C. FINANCING ACTIVITIES
A21: Dividends Paid | B21: ='Assumptions Sheet'!C18 -> -20500 | C21: ='Assumptions Sheet'!D18 -> -22150 | D21: ='Assumptions Sheet'!E18 -> -26300 | E21: ='Assumptions Sheet'!F18 -> -30650 | F21: ='Assumptions Sheet'!G18 -> -32650
A22: Share Buyback | B22: ='Assumptions Sheet'!C19 -> -17000 | C22: ='Assumptions Sheet'!D19 -> _ | D22: ='Assumptions Sheet'!E19 -> -18000 | E22: ='Assumptions Sheet'!F19 -> _ | F22: ='Assumptions Sheet'!G19 -> -19000
A23: Finance Costs Paid | B23: ='Assumptions Sheet'!C20 -> -780 | C23: ='Assumptions Sheet'!D20 -> -780 | D23: ='Assumptions Sheet'!E20 -> -780 | E23: ='Assumptions Sheet'!F20 -> -780 | F23: ='Assumptions Sheet'!G20 -> -780
A24: Net Cash from Financing Activities (CFF) | B24: =SUM(B21:B23) -> -38280 | C24: =SUM(C21:C23) -> -22930 | D24: =SUM(D21:D23) -> -45080 | E24: =SUM(E21:E23) -> -31430 | F24: =SUM(F21:F23) -> -52430
A25: D. NET MOVEMENT
A26: Effect of Exchange Rate Changes on Cash | B26: ='Assumptions Sheet'!C21 -> 100 | C26: ='Assumptions Sheet'!D21 -> 100 | D26: ='Assumptions Sheet'!E21 -> 100 | E26: ='Assumptions Sheet'!F21 -> 100 | F26: ='Assumptions Sheet'!G21 -> 100
A27: Net Increase / (Decrease) in Cash | B27: =B12+B18+B24+B26 -> 9567.1188 | C27: =C12+C18+C24+C26 -> 28418.269 | D27: =D12+D18+D24+D26 -> 16203.986 | E27: =E12+E18+E24+E26 -> 40718.405 | F27: =F12+F18+F24+F26 -> 24025.477
A29: Opening Cash & Cash Equivalents | B29: ='Cash Flow Statement'!G30 -> 14555 | C29: =B30 -> 24122.119 | D29: =C30 -> 27540.388 | E29: =D30 -> 24744.374 | F29: =E30 -> 30462.779
A30: Closing Cash & Cash Equivalents | B30: =B29+B27 -> 24122.119 | C30: =C29+C27-25000 -> 27540.388 | D30: =D29+D27-19000 -> 24744.374 | E30: =E29+E27-35000 -> 30462.779 | F30: =F29+F27-22000 -> 32488.255
A31: FREE CASH FLOW SUMMARY
A32: Free Cash Flow (CFO + Capex) | B32: =B12+B15 -> 48947.119 | C32: =C12+C15 -> 52448.269 | D32: =D12+D15 -> 62483.986 | E32: =E12+E15 -> 73348.405 | F32: =F12+F15 -> 77655.477
A33: FCF Conversion (FCF / PAT) | B33: =B32/B7 -> 1.0767428 | C33: =(C32)/C7 -> 1.0669767 | D33: =(D32)/D7 -> 1.0687321 | E33: =(E32)/E7 -> 1.0704629 | F33: =(F32)/F7 -> 1.0706989
A34: Capex / Revenue (Capex Intensity) | B34: =0.016 -> 0.016 | C34: =0.016 -> 0.016 | D34: =0.016 -> 0.016 | E34: =0.016 -> 0.016 | F34: =0.016 -> 0.016
